crawling_gocd/__init__.py
crawling_gocd/__main__.py
crawling_gocd/calculate_domain.py
crawling_gocd/calculator.py
crawling_gocd/crawler.py
crawling_gocd/four_key_metrics.py
crawling_gocd/gocd_domain.py
crawling_gocd/inputs_parser.py
crawling_gocd/outputs.py
crawling_gocd/portal.py
tests/integration/__init__.py
tests/unit/__init__.py
tests/unit/test_calculator.py
tests/unit/test_crawler.py
tests/unit/test_crawling_data_mapper.py
tests/unit/test_fixture.py
tests/unit/test_four_key_metrics.py
tests/unit/test_inputs_parser.py
tests/unit/test_output_csv.py
tests/unit/test_portal.py
crawling_gocd-1.3.0.dist-info/LICENSE
crawling_gocd-1.3.0.dist-info/METADATA
crawling_gocd-1.3.0.dist-info/WHEEL
crawling_gocd-1.3.0.dist-info/entry_points.txt
crawling_gocd-1.3.0.dist-info/top_level.txt
crawling_gocd-1.3.0.dist-info/RECORD
