Metadata-Version: 2.1
Name: crawling-gocd
Version: 1.3.0
Summary: crawling the gocd build histories of pipelines and calculate the metrics
Home-page: https://github.com/play-code-tools/crawling-gocd
Author: play-code-tools
Author-email: ellendan000@gmail.com
License: MIT
Platform: UNKNOWN
Classifier: License :: OSI Approved :: MIT License
Classifier: Programming Language :: Python :: 3
Classifier: Programming Language :: Python :: 3.7
Requires-Dist: requests-html
Requires-Dist: pyyaml
Requires-Dist: pyfunctional
